<?xml version="1.0" encoding="utf-8" ?>
<dwsync>
<file name="Duke Childrens Hospital.txt" local="128213637000000000" remote="128215089600000000" testing="0" />
<file name="aha.html" local="128214901280834000" remote="128215089600000000" testing="0" />
<file name="alexmov1.avi" local="128213637000000000" remote="128215089600000000" testing="0" />
<file name="asd.wav" local="128213836666900000" remote="128215089600000000" testing="0" />
<file name="aueulogy.html" local="128214932791402000" remote="128215089600000000" testing="0" />
<file name="dumc.html" local="128214901281054000" remote="128215089600000000" testing="0" />
<file name="glossary.html" local="128213637600000000" remote="128215089600000000" testing="0" />
<file name="gmeulogy.html" local="128214934537978000" remote="128215089600000000" testing="0" />
<file name="gpeulogy.html" local="128214939126560000" remote="128215089600000000" testing="0" />
<file name="heartn.wav" local="128213637600000000" remote="128215089600000000" testing="0" />
<file name="index.html" local="128213637600000000" remote="128215089600000000" testing="0" />
<file name="links.html" local="128213637600000000" remote="128215089600000000" testing="0" />
<file name="media.html" local="128213637600000000" remote="128215089600000000" testing="0" />
<file name="medical.html" local="128213637600000000" remote="128215089600000000" testing="0" />
<file name="memory.html" local="128214931869286000" remote="128215089600000000" testing="0" />
<file name="movies.html" local="128214948758562000" remote="128215089600000000" testing="0" />
<file name="nec.html" local="128213637600000000" remote="128215089600000000" testing="0" />
<file name="notepad_.ttf" local="128213637600000000" remote="128215089600000000" testing="0" />
<file name="pareulogy.html" local="128214939570848000" remote="128215089600000000" testing="0" />
<file name="pics.html" local="128214941015096000" remote="128215089600000000" testing="0" />
<file name="pprayer.html" local="128214901282184000" remote="128215089600000000" testing="0" />
<file name="stenta.mpg" local="128213638200000000" remote="128215090200000000" testing="0" />
<file name="stentb.mpg" local="128213638800000000" remote="128215090200000000" testing="0" />
<file name="story.html" local="128214901282354000" remote="128215090200000000" testing="0" />
<file name="thanks.html" local="128214901282684000" remote="128215090200000000" testing="0" />
<file name="uneulogy.html" local="128214940026368000" remote="128215090200000000" testing="0" />
<file name="vsd.wav" local="128213638800000000" remote="128215090200000000" testing="0" />
<file name="heart.html" local="128214901520656000" remote="128215089600000000" testing="0" />
<file name="newtemplate.html" local="128214901281914000" remote="128215089600000000" testing="0" />
</dwsync>